gauth_python/__init__.py
gauth_python/requests.py
tests/__init__.py
tests/test_gauth_python.py
gauth_python-0.1.8.dist-info/LICENSE
gauth_python-0.1.8.dist-info/METADATA
gauth_python-0.1.8.dist-info/WHEEL
gauth_python-0.1.8.dist-info/top_level.txt
gauth_python-0.1.8.dist-info/RECORD
