Metadata-Version: 2.1
Name: gauth-python
Version: 0.1.8
Summary: Python sdk from Gauth.
Home-page: https://github.com/GSM-MSG/GAuth-SDK-Python
Author: Noh Gaseong
Author-email: dev.yohan05@gmail.com
License: MIT
Platform: UNKNOWN
Classifier: Programming Language :: Python :: 3
Classifier: License :: OSI Approved :: MIT License
Classifier: Operating System :: OS Independent
Requires-Python: >=3.7
License-File: LICENSE
Requires-Dist: requests
